LICENSE
README.md
pyproject.toml
setup.py
modulus_ml/__init__.py
modulus_ml/comparator.py
modulus_ml/metrics.py
modulus_ml/utils.py
modulus_ml/visualizer.py
modulus_ml.egg-info/PKG-INFO
modulus_ml.egg-info/SOURCES.txt
modulus_ml.egg-info/dependency_links.txt
modulus_ml.egg-info/requires.txt
modulus_ml.egg-info/top_level.txt
tests/__init__.py
tests/test_comparator.py
tests/test_metrics.py
tests/test_utils.py