Metadata-Version: 2.1
Name: modulus-ml
Version: 0.1.0
Summary: A library for comparing and evaluating ML models
Home-page: https://github.com/kiojoel/modulus-ml
Author: Akinsanya Joel
Author-email: akinsanyajoel82@gmail.com
License: UNKNOWN
Platform: UNKNOWN
Classifier: Development Status :: 3 - Alpha
Classifier: Intended Audience :: Developers
Classifier: Programming Language :: Python :: 3
Classifier: License :: OSI Approved :: MIT License
Requires-Python: >=3.6
License-File: LICENSE
